[
    {
        "url": "https://hypackel.github.io/1/index.html",
        "imageSrc": "https://hypackel.github.io/1/meta/apple-touch-icon.png",
        "name": "1",
        "tags": "kids, html5"
      },
      {
        "url": "https://hypackel.github.io/1v1lol/index.html",
        "imageSrc": "https://hypackel.github.io/1v1lol/1v1lol.jpg",
        "name": "1v1.LOL",
        "tags": "action, shooting, unity"
      },
      {
        "url": "https://hypackel.github.io/4thandgoal/index.html",
        "imageSrc": "https://hypackel.github.io/4thandgoal/4th-and-goal-2022.avif",
        "name": "4th and goal 2022"
      }
]